claudepedia_mcp/__init__.py
claudepedia_mcp/server.py
claudepedia_mcp-0.5.0.dist-info/METADATA
claudepedia_mcp-0.5.0.dist-info/WHEEL
claudepedia_mcp-0.5.0.dist-info/entry_points.txt
claudepedia_mcp-0.5.0.dist-info/licenses/LICENSE
claudepedia_mcp-0.5.0.dist-info/RECORD
